metaflow_extensions/card_html/plugins/cards/html/__init__.py
metaflow_card_html-1.0.3.dist-info/LICENSE
metaflow_card_html-1.0.3.dist-info/METADATA
metaflow_card_html-1.0.3.dist-info/WHEEL
metaflow_card_html-1.0.3.dist-info/top_level.txt
metaflow_card_html-1.0.3.dist-info/RECORD
