Metadata-Version: 2.1
Name: metaflow-card-html
Version: 1.0.3
Summary: A metaflow card that renders HTML inputs.
Author: Outerbounds
Author-email: ville@outerbounds.co
License: Apache Software License 2.0
License-File: LICENSE
